bluetooth/__init__.py
bluetooth/_msbt.cp36-win_amd64.pyd
bluetooth/ble.py
bluetooth/bluez.py
bluetooth/btcommon.py
bluetooth/macos.py
bluetooth/msbt.py
bluetooth/widcomm.py
PyBluez-0.23.dist-info/COPYING
PyBluez-0.23.dist-info/METADATA
PyBluez-0.23.dist-info/WHEEL
PyBluez-0.23.dist-info/eager_resources.txt
PyBluez-0.23.dist-info/top_level.txt
PyBluez-0.23.dist-info/zip-safe
PyBluez-0.23.dist-info/RECORD
