Metadata-Version: 2.1
Name: PyBluez
Version: 0.23
Summary: Bluetooth Python extension module
Home-page: http://pybluez.github.io/
Author: Piotr Karulis
Author-email: ashuang@alum.mit.edu
License: GPL
Download-URL: https://github.com/pybluez/pybluez
Platform: UNKNOWN
Classifier: Development Status :: 4 - Beta
Classifier: License :: OSI Approved :: GNU General Public License (GPL)
Classifier: Programming Language :: Python
Classifier: Programming Language :: Python :: 2
Classifier: Programming Language :: Python :: 3
Classifier: Topic :: Communications
Provides-Extra: ble
Requires-Dist: gattlib (==0.20150805) ; extra == 'ble'
